{"cameraMode":{"drawMode":0,"name":"Shaded","section":"Shading Mode"},"sceneLighting":true,"audioPlay":false,"sceneViewState":{"showFog":true,"showMaterialUpdate":false,"showSkybox":true,"showFlares":true,"showImageEffects":true,"showParticleSystems":true},"in2DMode":false,"pivot":{"x":0.8436747789382935,"y":0.9553117156028748,"z":-0.49546271562576296},"rotation":{"x":-0.25016355514526369,"y":0.019177250564098359,"z":-0.004954957868903875,"w":-0.9680065512657166},"size":21.60896873474121,"orthographic":false}